pyspark3d/__init__.py
pyspark3d/checkers.py
pyspark3d/converters.py
pyspark3d/geometryObjects.py
pyspark3d/pyspark3d_conf.py
pyspark3d/queries.py
pyspark3d/repartitioning.py
pyspark3d/version.py
pyspark3d/visualisation.py
pyspark3d-0.3.1.dist-info/LICENSE
pyspark3d-0.3.1.dist-info/METADATA
pyspark3d-0.3.1.dist-info/WHEEL
pyspark3d-0.3.1.dist-info/top_level.txt
pyspark3d-0.3.1.dist-info/RECORD
